{
  "id": "其它语言/python/1.5pytorch库",
  "title": "PyTorch 使用指南",
  "description": "Create by yelv on 21 March Recently revised in 22 March 2025",
  "source": "@site/my-docs/其它语言/python/1.5pytorch库.md",
  "sourceDirName": "其它语言/python",
  "slug": "/其它语言/python/1.5pytorch库",
  "permalink": "/docs/其它语言/python/1.5pytorch库",
  "draft": false,
  "unlisted": false,
  "editUrl": "https://github.com/my-docs/其它语言/python/1.5pytorch库.md",
  "tags": [],
  "version": "current",
  "frontMatter": {},
  "sidebar": "tutorialSidebar",
  "previous": {
    "title": "1.4.3-Django框架",
    "permalink": "/docs/其它语言/python/1.4.3-Django框架"
  },
  "next": {
    "title": "-- IDEA 的使用",
    "permalink": "/docs/其它语言/java/-- IDEA 的使用"
  }
}