{
  "id": "JavaScript & TypeScript/JS 常用方法/-- JS日期处理",
  "title": "-- JS日期处理",
  "description": "Create by fall on 2022-02-15",
  "source": "@site/my-docs/JavaScript & TypeScript/JS 常用方法/-- JS日期处理.md",
  "sourceDirName": "JavaScript & TypeScript/JS 常用方法",
  "slug": "/JavaScript & TypeScript/JS 常用方法/-- JS日期处理",
  "permalink": "/docs/JavaScript & TypeScript/JS 常用方法/-- JS日期处理",
  "draft": false,
  "unlisted": false,
  "editUrl": "https://github.com/my-docs/JavaScript & TypeScript/JS 常用方法/-- JS日期处理.md",
  "tags": [],
  "version": "current",
  "frontMatter": {},
  "sidebar": "tutorialSidebar",
  "previous": {
    "title": "-- JS宿主对象操作",
    "permalink": "/docs/JavaScript & TypeScript/JS 常用方法/-- JS宿主对象操作"
  },
  "next": {
    "title": "-- JS的数组处理方法",
    "permalink": "/docs/JavaScript & TypeScript/JS 常用方法/-- JS的数组处理方法"
  }
}